eoq1/__init__.py
eoq1/commandparser.py
eoq1/queryparser.py
eoq1/resultparser.py
eoq1/valueparser.py
eoq1/actions/__init__.py
eoq1/actions/actionutils.py
eoq1/actions/externalactionhandler.py
eoq1/domains/__init__.py
eoq1/domains/localdomain.py
eoq1/domains/multiprocessingqueuedomainclient.py
eoq1/domains/multiprocessingqueuedomainhost.py
eoq1/domains/remotehttpdomain.py
eoq1/domains/simplepythondomainwrapper.py
eoq1/error/__init__.py
eoq1/error/error.py
eoq1/model/__init__.py
eoq1/model/model.py
eoq1/utils/__init__.py
eoq1/utils/csvconnector.py
eoq1-1.0.1.dist-info/LICENSE
eoq1-1.0.1.dist-info/METADATA
eoq1-1.0.1.dist-info/WHEEL
eoq1-1.0.1.dist-info/top_level.txt
eoq1-1.0.1.dist-info/RECORD
